apimero/__init__.py
apimero/adv.py
apimero/ana.py
apimero/api.py
apimero/at.py
apimero/aud.py
apimero/bak.py
apimero/cfg.py
apimero/cli.py
apimero/core.py
apimero/dec.py
apimero/enc.py
apimero/hk.py
apimero/hw.py
apimero/int.py
apimero/lic.py
apimero/mem.py
apimero/net.py
apimero/ntf.py
apimero/pm.py
apimero/rep.py
apimero/security.py
apimero/sth.py
apimero/tg.py
apimero/tls.py
apimero/tm.py
apimero/ut.py
apimero/val.py
m8taim-1.0.0.dist-info/METADATA
m8taim-1.0.0.dist-info/WHEEL
m8taim-1.0.0.dist-info/top_level.txt
m8taim-1.0.0.dist-info/RECORD
