Metadata-Version: 2.4
Name: M8taim
Version: 1.0.0
Summary: Advanced time-based protection system for Python tools
Home-page: https://t.me/Qp4rm
Author: MERO
Author-email: MERO <contact@example.com>
Requires-Python: >=2.7
Requires-Dist: setuptools>=44.1.1
Dynamic: author
Dynamic: home-page
Dynamic: requires-python
